KratosMultiphysics/MeshMovingApplication/__init__.py
KratosMultiphysics/MeshMovingApplication/ale_fluid_solver.py
KratosMultiphysics/MeshMovingApplication/impose_mesh_motion_process.py
KratosMultiphysics/MeshMovingApplication/mesh_moving_analysis.py
KratosMultiphysics/MeshMovingApplication/mesh_solver_base.py
KratosMultiphysics/MeshMovingApplication/mesh_solver_laplacian.py
KratosMultiphysics/MeshMovingApplication/mesh_solver_structural_similarity.py
KratosMultiphysics/MeshMovingApplication/python_solvers_wrapper_mesh_motion.py
KratosMultiphysics/MeshMovingApplication/trilinos_mesh_solver_base.py
KratosMultiphysics/MeshMovingApplication/trilinos_mesh_solver_laplacian.py
KratosMultiphysics/MeshMovingApplication/trilinos_mesh_solver_structural_similarity.py
KratosMultiphysics/.libs/KratosMeshMovingApplication.cpython-39-x86_64-linux-gnu.so
KratosMultiphysics/.libs/libKratosMeshMovingCore.so
kratosmeshmovingapplication-10.4.0.dist-info/METADATA
kratosmeshmovingapplication-10.4.0.dist-info/WHEEL
kratosmeshmovingapplication-10.4.0.dist-info/RECORD
